package/101917099.py
package/__init__.py
Topsis_Aeman_101917099-0.0.1.dist-info/LICENSE
Topsis_Aeman_101917099-0.0.1.dist-info/METADATA
Topsis_Aeman_101917099-0.0.1.dist-info/WHEEL
Topsis_Aeman_101917099-0.0.1.dist-info/top_level.txt
Topsis_Aeman_101917099-0.0.1.dist-info/RECORD
